pygosolnp/__init__.py
pygosolnp/evaluation_functions.py
pygosolnp/model.py
pygosolnp/pygosolnp.py
pygosolnp/resources.py
pygosolnp/sampling.py
pygosolnp/benchmarks/__init__.py
pygosolnp/benchmarks/electron.py
pygosolnp/benchmarks/permutations.py
python_examples/__init__.py
python_examples/example_electron.py
python_examples/example_electron_multiprocessed.py
python_examples/example_grid_sampling.py
python_examples/example_truncated_normal.py
tests/__init__.py
tests/evaluation_functions_test.py
tests/mock_random_test.py
tests/pygosolnp_electron_test.py
tests/pygosolnp_feature_test.py
tests/pygosolnp_input_validation_test.py
tests/pygosolnp_permutations_test.py
tests/resources.py
tests/mock/__init__.py
tests/mock/generate_random_numbers.py
tests/mock/mock_random.py
pygosolnp-2021.5.1.dist-info/LICENSE
pygosolnp-2021.5.1.dist-info/METADATA
pygosolnp-2021.5.1.dist-info/WHEEL
pygosolnp-2021.5.1.dist-info/top_level.txt
pygosolnp-2021.5.1.dist-info/RECORD
