Metadata-Version: 2.1
Name: pygosolnp
Version: 2021.5.1
Summary: This provides the GOSOLNP optimizaiton method.
Home-page: https://github.com/KristerSJakobsson/pygosolnp
Author: Krister Sune Jakobsson
Author-email: krister.s.jakobsson@gmail.com
License: Boost Software License
Platform: UNKNOWN
Classifier: Programming Language :: Python :: 3
Classifier: License :: OSI Approved :: MIT License
Classifier: Operating System :: OS Independent
Requires-Python: >=3.6
Requires-Dist: pysolnp
